{
    "0": {
        "characters": [
            {
                "name": "Arizona Raines",
                "api_detail_url": "http://comicvine.gamespot.com/api/character/4005-84321/",
                "id": 84321,
                "site_detail_url": "http://comicvine.gamespot.com/arizona-raines/4005-84321/"
            },
            {
                "name": "The Whip",
                "api_detail_url": "http://comicvine.gamespot.com/api/character/4005-84322/",
                "id": 84322,
                "site_detail_url": "http://comicvine.gamespot.com/the-whip/4005-84322/"
            },
            {
                "name": "Two-Gun Lil",
                "api_detail_url": "http://comicvine.gamespot.com/api/character/4005-84323/",
                "id": 84323,
                "site_detail_url": "http://comicvine.gamespot.com/two-gun-lil/4005-84323/"
            }
        ],
        "description": "<p>Continued from <a data-ref-id=\"4050-18074\" href=\"/crack-comics/4050-18074\" slug=\"crack-comics\"> Crack Comics</a>.</p>",
        "aliases": null,
        "publisher": {
            "name": "Quality Comics",
            "api_detail_url": "http://comicvine.gamespot.com/api/publisher/4010-15/",
            "id": 15
        },
        "name": "Crack Western",
        "image": {
            "icon_url": "http://static1.comicvine.com/uploads/square_avatar/0/4/58764-1248-91759-1-crack-western.jpg",
            "medium_url": "http://static2.comicvine.com/uploads/scale_medium/0/4/58764-1248-91759-1-crack-western.jpg",
            "thumb_url": "http://static6.comicvine.com/uploads/scale_avatar/0/4/58764-1248-91759-1-crack-western.jpg",
            "tiny_url": "http://static7.comicvine.com/uploads/square_mini/0/4/58764-1248-91759-1-crack-western.jpg",
            "super_url": "http://static5.comicvine.com/uploads/scale_large/0/4/58764-1248-91759-1-crack-western.jpg",
            "screen_url": "http://static3.comicvine.com/uploads/screen_medium/0/4/58764-1248-91759-1-crack-western.jpg",
            "small_url": "http://static4.comicvine.com/uploads/scale_small/0/4/58764-1248-91759-1-crack-western.jpg"
        }
    },
    "1": {
        "characters": [
            {
                "name": "Black Roger",
                "api_detail_url": "http://comicvine.gamespot.com/api/character/4005-81539/",
                "id": 81539,
                "site_detail_url": "http://comicvine.gamespot.com/black-roger/4005-81539/"
            },
            {
                "name": "Captain Daring",
                "api_detail_url": "http://comicvine.gamespot.com/api/character/4005-81556/",
                "id": 81556,
                "site_detail_url": "http://comicvine.gamespot.com/captain-daring/4005-81556/"
            }
        ],
        "description": "<p>Buccaneers is replacing <a data-ref-id=\"4050-28010\" href=\"/kid-eternity/4050-28010\" slug=\"kid-eternity\">  Kid Eternity</a> (#1-18). Follows adventures of pirates, most prominent character is <a data-ref-id=\"4005-47203\" href=\"/captain-daring/4005-47203\" slug=\"captain-daring\"> Captain Daring</a>. Lasted 9 issues.\u00a0<br/>\u00a0<br/> </p><p>During its short 9 issue run Buccaneers had the same five characters each issue in stories that were almost identical to each other.  \u00a0<br/>\u00a0<br/>The line-up was\u00a0<br/>\u00a0<br/>Captain Daring:  The lead character, who pretended to be a pirate but was sailing the Spanish Main out to bring them all down, Captain Daring was pretty obviously modeled on Errol Flynn.\u00a0<br/>\u00a0<br/>The Spanish Main: which featured a character called Dick Warr, who some thought was a pirate, but was really out to destroy all their kind, the only way to tell this feature from the first was the art wasn't as good and it only had half as many pages.\u00a0<br/>\u00a0<br/>Eric Falcon: Solider of Fortune: Still sailing the Spanish Main, still fencing with pirates, but at least he was a bit of a rogue and wasn't out to end piracy single-handed.  \u00a0<br/>\u00a0<br/>A two page text piece as was required by the Post Office so they could send comics through the mail by 3 class mail.  \u00a0<br/>\u00a0<br/>Black Roger: Shanghaied from an English port he escapes, puts on a mask, calls himself Black Roger and dedicates himself to sinking every pirate he can find. Basically this is Captain Blood reduced to 6 pages and put in a mask.... guess who played Captain Blood in the movies... Yep, so with the last feature of this comic it circles around on itself. Art by Reed Crandell was good.</p>",
        "aliases": null,
        "publisher": {
            "name": "Quality Comics",
            "api_detail_url": "http://comicvine.gamespot.com/api/publisher/4010-15/",
            "id": 15
        },
        "name": "Buccaneers",
        "image": {
            "icon_url": "http://static1.comicvine.com/uploads/square_avatar/0/4/71736-1332-104734-1-buccaneers.jpg",
            "medium_url": "http://static2.comicvine.com/uploads/scale_medium/0/4/71736-1332-104734-1-buccaneers.jpg",
            "thumb_url": "http://static6.comicvine.com/uploads/scale_avatar/0/4/71736-1332-104734-1-buccaneers.jpg",
            "tiny_url": "http://static7.comicvine.com/uploads/square_mini/0/4/71736-1332-104734-1-buccaneers.jpg",
            "super_url": "http://static5.comicvine.com/uploads/scale_large/0/4/71736-1332-104734-1-buccaneers.jpg",
            "screen_url": "http://static3.comicvine.com/uploads/screen_medium/0/4/71736-1332-104734-1-buccaneers.jpg",
            "small_url": "http://static4.comicvine.com/uploads/scale_small/0/4/71736-1332-104734-1-buccaneers.jpg"
        }
    },
    "2": {
        "characters": [],
        "description": null,
        "aliases": null,
        "publisher": {
            "name": "Quality Comics",
            "api_detail_url": "http://comicvine.gamespot.com/api/publisher/4010-15/",
            "id": 15
        },
        "name": "Forbidden Love",
        "image": {
            "icon_url": "http://static1.comicvine.com/uploads/square_avatar/0/4/57340-10729-90335-1-forbidden-love.jpg",
            "medium_url": "http://static2.comicvine.com/uploads/scale_medium/0/4/57340-10729-90335-1-forbidden-love.jpg",
            "thumb_url": "http://static6.comicvine.com/uploads/scale_avatar/0/4/57340-10729-90335-1-forbidden-love.jpg",
            "tiny_url": "http://static7.comicvine.com/uploads/square_mini/0/4/57340-10729-90335-1-forbidden-love.jpg",
            "super_url": "http://static5.comicvine.com/uploads/scale_large/0/4/57340-10729-90335-1-forbidden-love.jpg",
            "screen_url": "http://static3.comicvine.com/uploads/screen_medium/0/4/57340-10729-90335-1-forbidden-love.jpg",
            "small_url": "http://static4.comicvine.com/uploads/scale_small/0/4/57340-10729-90335-1-forbidden-love.jpg"
        }
    },
    "3": {
        "characters": [
            {
                "name": "Candy O'Connor",
                "api_detail_url": "http://comicvine.gamespot.com/api/character/4005-77324/",
                "id": 77324,
                "site_detail_url": "http://comicvine.gamespot.com/candy-oconnor/4005-77324/"
            }
        ],
        "description": null,
        "aliases": null,
        "publisher": {
            "name": "Quality Comics",
            "api_detail_url": "http://comicvine.gamespot.com/api/publisher/4010-15/",
            "id": 15
        },
        "name": "Candy",
        "image": {
            "icon_url": "http://static1.comicvine.com/uploads/square_avatar/0/4/58577-10784-91572-1-candy.jpg",
            "medium_url": "http://static2.comicvine.com/uploads/scale_medium/0/4/58577-10784-91572-1-candy.jpg",
            "thumb_url": "http://static6.comicvine.com/uploads/scale_avatar/0/4/58577-10784-91572-1-candy.jpg",
            "tiny_url": "http://static7.comicvine.com/uploads/square_mini/0/4/58577-10784-91572-1-candy.jpg",
            "super_url": "http://static5.comicvine.com/uploads/scale_large/0/4/58577-10784-91572-1-candy.jpg",
            "screen_url": "http://static3.comicvine.com/uploads/screen_medium/0/4/58577-10784-91572-1-candy.jpg",
            "small_url": "http://static4.comicvine.com/uploads/scale_small/0/4/58577-10784-91572-1-candy.jpg"
        }
    },
    "4": {
        "characters": [],
        "description": null,
        "aliases": null,
        "publisher": {
            "name": "Quality Comics",
            "api_detail_url": "http://comicvine.gamespot.com/api/publisher/4010-15/",
            "id": 15
        },
        "name": "Gabby",
        "image": {
            "icon_url": "http://static1.comicvine.com/uploads/square_avatar/6/62047/1279504-gabby__3___page_1.jpg",
            "medium_url": "http://static2.comicvine.com/uploads/scale_medium/6/62047/1279504-gabby__3___page_1.jpg",
            "thumb_url": "http://static6.comicvine.com/uploads/scale_avatar/6/62047/1279504-gabby__3___page_1.jpg",
            "tiny_url": "http://static7.comicvine.com/uploads/square_mini/6/62047/1279504-gabby__3___page_1.jpg",
            "super_url": "http://static5.comicvine.com/uploads/scale_large/6/62047/1279504-gabby__3___page_1.jpg",
            "screen_url": "http://static3.comicvine.com/uploads/screen_medium/6/62047/1279504-gabby__3___page_1.jpg",
            "small_url": "http://static4.comicvine.com/uploads/scale_small/6/62047/1279504-gabby__3___page_1.jpg"
        }
    },
    "5": {
        "characters": [],
        "description": "<p>Published from November 1949 to September 1950 with 6 total issues numbered 1-6.</p>",
        "aliases": null,
        "publisher": {
            "name": "Quality Comics",
            "api_detail_url": "http://comicvine.gamespot.com/api/publisher/4010-15/",
            "id": 15
        },
        "name": "Hollywood Secrets",
        "image": {
            "icon_url": "http://static1.comicvine.com/uploads/square_avatar/0/4/59992-10850-92987-1-hollywood-secrets.jpg",
            "medium_url": "http://static2.comicvine.com/uploads/scale_medium/0/4/59992-10850-92987-1-hollywood-secrets.jpg",
            "thumb_url": "http://static6.comicvine.com/uploads/scale_avatar/0/4/59992-10850-92987-1-hollywood-secrets.jpg",
            "tiny_url": "http://static7.comicvine.com/uploads/square_mini/0/4/59992-10850-92987-1-hollywood-secrets.jpg",
            "super_url": "http://static5.comicvine.com/uploads/scale_large/0/4/59992-10850-92987-1-hollywood-secrets.jpg",
            "screen_url": "http://static3.comicvine.com/uploads/screen_medium/0/4/59992-10850-92987-1-hollywood-secrets.jpg",
            "small_url": "http://static4.comicvine.com/uploads/scale_small/0/4/59992-10850-92987-1-hollywood-secrets.jpg"
        }
    },
    "6": {
        "characters": [
            {
                "name": "Marmaduke Mouse",
                "api_detail_url": "http://comicvine.gamespot.com/api/character/4005-2758/",
                "id": 2758,
                "site_detail_url": "http://comicvine.gamespot.com/marmaduke-mouse/4005-2758/"
            },
            {
                "name": "Rollo Raccoon",
                "api_detail_url": "http://comicvine.gamespot.com/api/character/4005-16399/",
                "id": 16399,
                "site_detail_url": "http://comicvine.gamespot.com/rollo-raccoon/4005-16399/"
            },
            {
                "name": "Louie The Lion",
                "api_detail_url": "http://comicvine.gamespot.com/api/character/4005-95404/",
                "id": 95404,
                "site_detail_url": "http://comicvine.gamespot.com/louie-the-lion/4005-95404/"
            }
        ],
        "description": null,
        "aliases": null,
        "publisher": {
            "name": "Quality Comics",
            "api_detail_url": "http://comicvine.gamespot.com/api/publisher/4010-15/",
            "id": 15
        },
        "name": "Marmaduke Mouse",
        "image": {
            "icon_url": "http://static1.comicvine.com/uploads/square_avatar/0/4/69920-11655-102918-1-marmaduke-mouse.jpg",
            "medium_url": "http://static2.comicvine.com/uploads/scale_medium/0/4/69920-11655-102918-1-marmaduke-mouse.jpg",
            "thumb_url": "http://static6.comicvine.com/uploads/scale_avatar/0/4/69920-11655-102918-1-marmaduke-mouse.jpg",
            "tiny_url": "http://static7.comicvine.com/uploads/square_mini/0/4/69920-11655-102918-1-marmaduke-mouse.jpg",
            "super_url": "http://static5.comicvine.com/uploads/scale_large/0/4/69920-11655-102918-1-marmaduke-mouse.jpg",
            "screen_url": "http://static3.comicvine.com/uploads/screen_medium/0/4/69920-11655-102918-1-marmaduke-mouse.jpg",
            "small_url": "http://static4.comicvine.com/uploads/scale_small/0/4/69920-11655-102918-1-marmaduke-mouse.jpg"
        }
    },
    "7": {
        "characters": [
            {
                "name": "Kelly Poole",
                "api_detail_url": "http://comicvine.gamespot.com/api/character/4005-1771/",
                "id": 1771,
                "site_detail_url": "http://comicvine.gamespot.com/kelly-poole/4005-1771/"
            },
            {
                "name": "Atomictot",
                "api_detail_url": "http://comicvine.gamespot.com/api/character/4005-124480/",
                "id": 124480,
                "site_detail_url": "http://comicvine.gamespot.com/atomictot/4005-124480/"
            }
        ],
        "description": null,
        "aliases": null,
        "publisher": {
            "name": "Quality Comics",
            "api_detail_url": "http://comicvine.gamespot.com/api/publisher/4010-15/",
            "id": 15
        },
        "name": "All Humor Comics",
        "image": {
            "icon_url": "http://static1.comicvine.com/uploads/square_avatar/0/4/71460-12012-104458-1-all-humor-comics.jpg",
            "medium_url": "http://static2.comicvine.com/uploads/scale_medium/0/4/71460-12012-104458-1-all-humor-comics.jpg",
            "thumb_url": "http://static6.comicvine.com/uploads/scale_avatar/0/4/71460-12012-104458-1-all-humor-comics.jpg",
            "tiny_url": "http://static7.comicvine.com/uploads/square_mini/0/4/71460-12012-104458-1-all-humor-comics.jpg",
            "super_url": "http://static5.comicvine.com/uploads/scale_large/0/4/71460-12012-104458-1-all-humor-comics.jpg",
            "screen_url": "http://static3.comicvine.com/uploads/screen_medium/0/4/71460-12012-104458-1-all-humor-comics.jpg",
            "small_url": "http://static4.comicvine.com/uploads/scale_small/0/4/71460-12012-104458-1-all-humor-comics.jpg"
        }
    },
    "8": {
        "characters": [],
        "description": "<p>Series continued from: Diary Loves (Quality Comics, 1949) #31</p><p>Series continues as: Girls in Love (Quality Comics, 1955) #46</p>",
        "aliases": null,
        "publisher": {
            "name": "Quality Comics",
            "api_detail_url": "http://comicvine.gamespot.com/api/publisher/4010-15/",
            "id": 15
        },
        "name": "G.I. Sweethearts",
        "image": {
            "icon_url": "http://static1.comicvine.com/uploads/square_avatar/0/4/71796-12038-104794-1-g-i-sweethearts.jpg",
            "medium_url": "http://static2.comicvine.com/uploads/scale_medium/0/4/71796-12038-104794-1-g-i-sweethearts.jpg",
            "thumb_url": "http://static6.comicvine.com/uploads/scale_avatar/0/4/71796-12038-104794-1-g-i-sweethearts.jpg",
            "tiny_url": "http://static7.comicvine.com/uploads/square_mini/0/4/71796-12038-104794-1-g-i-sweethearts.jpg",
            "super_url": "http://static5.comicvine.com/uploads/scale_large/0/4/71796-12038-104794-1-g-i-sweethearts.jpg",
            "screen_url": "http://static3.comicvine.com/uploads/screen_medium/0/4/71796-12038-104794-1-g-i-sweethearts.jpg",
            "small_url": "http://static4.comicvine.com/uploads/scale_small/0/4/71796-12038-104794-1-g-i-sweethearts.jpg"
        }
    },
    "9": {
        "characters": [
            {
                "name": "Adolf Hitler",
                "api_detail_url": "http://comicvine.gamespot.com/api/character/4005-9671/",
                "id": 9671,
                "site_detail_url": "http://comicvine.gamespot.com/adolf-hitler/4005-9671/"
            },
            {
                "name": "Spider",
                "api_detail_url": "http://comicvine.gamespot.com/api/character/4005-9978/",
                "id": 9978,
                "site_detail_url": "http://comicvine.gamespot.com/spider/4005-9978/"
            },
            {
                "name": "Richard Grey Jr.",
                "api_detail_url": "http://comicvine.gamespot.com/api/character/4005-30198/",
                "id": 30198,
                "site_detail_url": "http://comicvine.gamespot.com/richard-grey-jr/4005-30198/"
            },
            {
                "name": "Father Pierre",
                "api_detail_url": "http://comicvine.gamespot.com/api/character/4005-30201/",
                "id": 30201,
                "site_detail_url": "http://comicvine.gamespot.com/father-pierre/4005-30201/"
            },
            {
                "name": "Franklin D. Roosevelt",
                "api_detail_url": "http://comicvine.gamespot.com/api/character/4005-31595/",
                "id": 31595,
                "site_detail_url": "http://comicvine.gamespot.com/franklin-d-roosevelt/4005-31595/"
            },
            {
                "name": "Hermann G\u00f6ring",
                "api_detail_url": "http://comicvine.gamespot.com/api/character/4005-31684/",
                "id": 31684,
                "site_detail_url": "http://comicvine.gamespot.com/hermann-goring/4005-31684/"
            },
            {
                "name": "Joseph Goebbels",
                "api_detail_url": "http://comicvine.gamespot.com/api/character/4005-31685/",
                "id": 31685,
                "site_detail_url": "http://comicvine.gamespot.com/joseph-goebbels/4005-31685/"
            },
            {
                "name": "Captain Triumph",
                "api_detail_url": "http://comicvine.gamespot.com/api/character/4005-36911/",
                "id": 36911,
                "site_detail_url": "http://comicvine.gamespot.com/captain-triumph/4005-36911/"
            },
            {
                "name": "Madame Fatal",
                "api_detail_url": "http://comicvine.gamespot.com/api/character/4005-41364/",
                "id": 41364,
                "site_detail_url": "http://comicvine.gamespot.com/madame-fatal/4005-41364/"
            },
            {
                "name": "The Clock",
                "api_detail_url": "http://comicvine.gamespot.com/api/character/4005-53494/",
                "id": 53494,
                "site_detail_url": "http://comicvine.gamespot.com/the-clock/4005-53494/"
            },
            {
                "name": "Jane Arden",
                "api_detail_url": "http://comicvine.gamespot.com/api/character/4005-60913/",
                "id": 60913,
                "site_detail_url": "http://comicvine.gamespot.com/jane-arden/4005-60913/"
            },
            {
                "name": "Red Torpedo",
                "api_detail_url": "http://comicvine.gamespot.com/api/character/4005-62623/",
                "id": 62623,
                "site_detail_url": "http://comicvine.gamespot.com/red-torpedo/4005-62623/"
            },
            {
                "name": "Molly the Model",
                "api_detail_url": "http://comicvine.gamespot.com/api/character/4005-63536/",
                "id": 63536,
                "site_detail_url": "http://comicvine.gamespot.com/molly-the-model/4005-63536/"
            },
            {
                "name": "Slap Happy Pappy",
                "api_detail_url": "http://comicvine.gamespot.com/api/character/4005-75491/",
                "id": 75491,
                "site_detail_url": "http://comicvine.gamespot.com/slap-happy-pappy/4005-75491/"
            },
            {
                "name": "Pen Miller",
                "api_detail_url": "http://comicvine.gamespot.com/api/character/4005-75930/",
                "id": 75930,
                "site_detail_url": "http://comicvine.gamespot.com/pen-miller/4005-75930/"
            },
            {
                "name": "Biff",
                "api_detail_url": "http://comicvine.gamespot.com/api/character/4005-75954/",
                "id": 75954,
                "site_detail_url": "http://comicvine.gamespot.com/biff/4005-75954/"
            },
            {
                "name": "Black Shark",
                "api_detail_url": "http://comicvine.gamespot.com/api/character/4005-76232/",
                "id": 76232,
                "site_detail_url": "http://comicvine.gamespot.com/black-shark/4005-76232/"
            },
            {
                "name": "Biff Banks",
                "api_detail_url": "http://comicvine.gamespot.com/api/character/4005-76509/",
                "id": 76509,
                "site_detail_url": "http://comicvine.gamespot.com/biff-banks/4005-76509/"
            },
            {
                "name": "Big Shot",
                "api_detail_url": "http://comicvine.gamespot.com/api/character/4005-76510/",
                "id": 76510,
                "site_detail_url": "http://comicvine.gamespot.com/big-shot/4005-76510/"
            },
            {
                "name": "Kim Meredith",
                "api_detail_url": "http://comicvine.gamespot.com/api/character/4005-76763/",
                "id": 76763,
                "site_detail_url": "http://comicvine.gamespot.com/kim-meredith/4005-76763/"
            },
            {
                "name": "Hack O'Hara",
                "api_detail_url": "http://comicvine.gamespot.com/api/character/4005-76766/",
                "id": 76766,
                "site_detail_url": "http://comicvine.gamespot.com/hack-ohara/4005-76766/"
            },
            {
                "name": "Inkie",
                "api_detail_url": "http://comicvine.gamespot.com/api/character/4005-86876/",
                "id": 86876,
                "site_detail_url": "http://comicvine.gamespot.com/inkie/4005-86876/"
            },
            {
                "name": "Beezy Bumble",
                "api_detail_url": "http://comicvine.gamespot.com/api/character/4005-86879/",
                "id": 86879,
                "site_detail_url": "http://comicvine.gamespot.com/beezy-bumble/4005-86879/"
            },
            {
                "name": "Batch Bachelor",
                "api_detail_url": "http://comicvine.gamespot.com/api/character/4005-86880/",
                "id": 86880,
                "site_detail_url": "http://comicvine.gamespot.com/batch-bachelor/4005-86880/"
            },
            {
                "name": "Mr. Pointer",
                "api_detail_url": "http://comicvine.gamespot.com/api/character/4005-87178/",
                "id": 87178,
                "site_detail_url": "http://comicvine.gamespot.com/mr-pointer/4005-87178/"
            },
            {
                "name": "Carim Bombay",
                "api_detail_url": "http://comicvine.gamespot.com/api/character/4005-87184/",
                "id": 87184,
                "site_detail_url": "http://comicvine.gamespot.com/carim-bombay/4005-87184/"
            },
            {
                "name": "A. Spade",
                "api_detail_url": "http://comicvine.gamespot.com/api/character/4005-87185/",
                "id": 87185,
                "site_detail_url": "http://comicvine.gamespot.com/a-spade/4005-87185/"
            },
            {
                "name": "Z. Spade",
                "api_detail_url": "http://comicvine.gamespot.com/api/character/4005-87186/",
                "id": 87186,
                "site_detail_url": "http://comicvine.gamespot.com/z-spade/4005-87186/"
            },
            {
                "name": "Jack Cole",
                "api_detail_url": "http://comicvine.gamespot.com/api/character/4005-93310/",
                "id": 93310,
                "site_detail_url": "http://comicvine.gamespot.com/jack-cole/4005-93310/"
            },
            {
                "name": "Volto",
                "api_detail_url": "http://comicvine.gamespot.com/api/character/4005-115733/",
                "id": 115733,
                "site_detail_url": "http://comicvine.gamespot.com/volto/4005-115733/"
            }
        ],
        "description": "<p>Crack Comics was and anthology volume produced by Fawcett/Quality in the 1940s. As of November, 1949 Crack Comics are being published as <a data-ref-id=\"4050-1248\" href=\"/crack-western/4050-1248\" slug=\"crack-western\"> Crack Western</a>, continuing numbering with issue #63.<br/></p>",
        "aliases": null,
        "publisher": {
            "name": "Quality Comics",
            "api_detail_url": "http://comicvine.gamespot.com/api/publisher/4010-15/",
            "id": 15
        },
        "name": "Crack Comics",
        "image": {
            "icon_url": "http://static1.comicvine.com/uploads/square_avatar/0/1494/86156-18074-105852-1-crack-comics.jpg",
            "medium_url": "http://static2.comicvine.com/uploads/scale_medium/0/1494/86156-18074-105852-1-crack-comics.jpg",
            "thumb_url": "http://static6.comicvine.com/uploads/scale_avatar/0/1494/86156-18074-105852-1-crack-comics.jpg",
            "tiny_url": "http://static7.comicvine.com/uploads/square_mini/0/1494/86156-18074-105852-1-crack-comics.jpg",
            "super_url": "http://static5.comicvine.com/uploads/scale_large/0/1494/86156-18074-105852-1-crack-comics.jpg",
            "screen_url": "http://static3.comicvine.com/uploads/screen_medium/0/1494/86156-18074-105852-1-crack-comics.jpg",
            "small_url": "http://static4.comicvine.com/uploads/scale_small/0/1494/86156-18074-105852-1-crack-comics.jpg"
        }
    }
}